{
	"name": "block.sculktransporting.sculk_transmitter",
	"icon": "sculktransporting:sculk_transmitter",
	"category": "sculktransporting:default",
	"sortnum": 4,
	"pages": [
		{
			"type": "spotlight",
			"item": "sculktransporting:sculk_transmitter",
			"text": "book.sculktransporting.sculk_transmitter.page1"
		},
		{
			"type": "patchouli:crafting",
			"recipe": "sculktransporting:sculk_transmitter",
			"title": "book.sculktransporting.crafting",
			"text": "book.sculktransporting.sculk_transmitter.page2"
		}
	]
}